MANIFEST.in
README.md
setup.py
wick/__init__.py
wick/cli.py
wick/common.py
wick.egg-info/PKG-INFO
wick.egg-info/SOURCES.txt
wick.egg-info/dependency_links.txt
wick.egg-info/entry_points.txt
wick.egg-info/top_level.txt
wick/generators/__init__.py
wick/generators/csharp/__init__.py
wick/generators/csharp/filters.py
wick/generators/csharp/templates/main.jinja2
wick/generators/javascript/__init__.py
wick/generators/javascript/filters.py
wick/generators/javascript/templates/main.jinja2
wick/generators/markdown/__init__.py
wick/generators/markdown/common.py
wick/generators/markdown/document.py
wick/generators/markdown/elements.py
wick/generators/python/__init__.py
wick/generators/python/filters.py
wick/generators/python/templates/main.jinja2
wick/generators/python/templates/test.jinja2
wick/generators/template/__init__.py
wick/generators/template/filters.py
wick/parser/__init__.py
wick/parser/common.py
wick/parser/lexer.py
wick/parser/parser.py