Metadata-Version: 2.1
Name: wick
Version: 1.1.0
Summary: UNKNOWN
Home-page: https://github.com/JoshuaSkelly/wick
Author: Joshua Skelton
Author-email: joshua.skelton@gmail.com
License: MIT
Platform: UNKNOWN
Classifier: Intended Audience :: Developers
Classifier: License :: OSI Approved :: MIT License
Classifier: Operating System :: OS Independent
Classifier: Programming Language :: Python
Classifier: Programming Language :: Python :: 3
Classifier: Topic :: Software Development :: Libraries :: Python Modules
